tailgen/__init__.py
tailgen/__main__.py
tailgen/cli.py
tailgen/fastapi_app/__init__.py
tailgen/fastapi_app/setup_files/base.txt
tailgen/fastapi_app/setup_files/main.txt
tailgen/fastapi_app/setup_files/tailwind_config.txt
tailgen/flask_app/__init__.py
tailgen/flask_app/setup_files/app.txt
tailgen/flask_app/setup_files/index.txt
tailgen/flask_app/setup_files/tailwind_config.txt
tailgen/helpers.py
tailgen-1.3.0.dist-info/LICENSE.txt
tailgen-1.3.0.dist-info/METADATA
tailgen-1.3.0.dist-info/WHEEL
tailgen-1.3.0.dist-info/entry_points.txt
tailgen-1.3.0.dist-info/RECORD
