Metadata-Version: 2.1
Name: tailgen
Version: 1.3.0
Summary: TailGen is a command-line interface (CLI) tool designed to simplify the process of generating Flask or FastAPI projects with Tailwind CSS integration. With TailGen, you can quickly set up a new web application project with the necessary files and directory structures, saving you time and effort in the initial setup phase.
License: LICENSE.txt
Author: Nicholas Ikiroma
Author-email: nicholasikiroma@gmail.com
Requires-Python: >=3.10,<4.0
Classifier: License :: Other/Proprietary License
Classifier: Programming Language :: Python :: 3
Classifier: Programming Language :: Python :: 3.10
Classifier: Programming Language :: Python :: 3.11
Classifier: Programming Language :: Python :: 3.12
Requires-Dist: pytest (>=8.2.0,<9.0.0)
Requires-Dist: rich (>=13.7.1,<14.0.0)
Requires-Dist: typer (>=0.12.3,<0.13.0)
